gsc_api_handler/__about__.py
gsc_api_handler/__init__.py
gsc_api_handler/auth.py
gsc_api_handler/fetcher.py
gsc_api_handler/utils.py
gsc_api_handler-1.0.5.dist-info/METADATA
gsc_api_handler-1.0.5.dist-info/WHEEL
gsc_api_handler-1.0.5.dist-info/licenses/LICENSE.txt
gsc_api_handler-1.0.5.dist-info/RECORD
