Metadata-Version: 2.4
Name: gsc-api-handler
Version: 1.0.5
Summary: Fetches data from Google Search Console and stores it into SQLite
Project-URL: Documentation, https://github.com/oksidans/gsc-api-handler#readme
Project-URL: Issues, https://github.com/oksidans/gsc-api-handler/issues
Project-URL: Source, https://github.com/oksidans/gsc-api-handler
Author-email: oksidans <zmiroljub.zivkovic@gmail.com>
License-Expression: MIT
License-File: LICENSE.txt
Classifier: Development Status :: 4 - Beta
Classifier: Programming Language :: Python
Classifier: Programming Language :: Python :: 3.9
Classifier: Programming Language :: Python :: 3.10
Classifier: Programming Language :: Python :: 3.11
Classifier: Programming Language :: Python :: 3.12
Classifier: Programming Language :: Python :: Implementation :: CPython
Classifier: Programming Language :: Python :: Implementation :: PyPy
Requires-Python: >=3.9
Requires-Dist: google-api-python-client>=2.100.0
Requires-Dist: google-auth-httplib2>=0.1.0
Requires-Dist: google-auth-oauthlib>=1.0.0
Requires-Dist: google-auth>=2.27.0
Requires-Dist: oauthlib>=3.0.0
Requires-Dist: python-dateutil>=2.8.2
Requires-Dist: python-decouple>=3.8
Requires-Dist: requests>=2.18.0
